pysmartrip/__init__.py
pysmartrip/card.py
pysmartrip/smartrip.py
pysmartrip/trip.py
pysmartrip-0.0.1.dist-info/licenses/LICENSE
pysmartrip-0.0.1.dist-info/METADATA
pysmartrip-0.0.1.dist-info/WHEEL
pysmartrip-0.0.1.dist-info/top_level.txt
pysmartrip-0.0.1.dist-info/RECORD
