Metadata-Version: 2.4
Name: pysmartrip
Version: 0.0.1
Summary: Library for interacting with WMATA SmarTrip data
Author-email: Matthew Rinaldi <me@mmae.kr>
License-Expression: MIT
Project-URL: Homepage, https://github.com/mmaekr/pysmartrip
Project-URL: Issues, https://github.com/mmaekr/pysmartrip/issues
Requires-Python: >=3.10
License-File: LICENSE
Requires-Dist: requests
Dynamic: license-file
